snakefusion-0.1.6.dist-info/METADATA
snakefusion-0.1.6.dist-info/WHEEL
snakefusion/tests/analogy.fifu
snakefusion/tests/conftest.py
snakefusion/tests/embeddings.dims.txt
snakefusion/tests/embeddings.fifu
snakefusion/tests/embeddings.floret
snakefusion/tests/embeddings.txt
snakefusion/tests/floret-check.txt
snakefusion/tests/similarity-pq.fifu
snakefusion/tests/similarity.fifu
snakefusion/tests/subword.fifu
snakefusion/tests/test_analogy.py
snakefusion/tests/test_embeddings.py
snakefusion/tests/test_quantization.py
snakefusion/tests/test_similarity.py
snakefusion/tests/test_vocab.py
snakefusion/__init__.py
snakefusion/snakefusion.pyd
snakefusion-0.1.6.dist-info/RECORD
